{
  "id": 6572,
  "name": "Kinder Mittelalterkleid Eleanor, langarm, blau",
  "slug": "",
  "permalink": "https://die-handelsgilde.de/?post_type=product&p=6572",
  "date_created": "2025-10-10T17:10:53",
  "date_created_gmt": "2025-10-10T15:10:53",
  "date_modified": "2025-10-14T20:36:56",
  "date_modified_gmt": "2025-10-14T18:36:56",
  "type": "variable",
  "status": "draft",
  "featured": false,
  "catalog_visibility": "visible",
  "description": "<h1>Kinder Mittelalterkleid Eleanor, langarm, blau</h1>\n<p>Ein eng geschnittenes Kinderkleid im mittelalterlichen Stil, bekannt für seinen zweifarbigen Lagenlook und die goldene Bordüre. Schnürungen vorne und hinten sorgen für einen authentischen Look.</p>\n<h3>Material &amp; Verarbeitung</h3>\n<p>Hochwertige Fertigung mit viel Liebe zum historischen Detail und handwerklicher Präzision.</p>\n<ul>\n<li>Erhältlich in den Größen 110, 128, 146</li>\n<li>Farben: Blau/Blaugrau, auch in Rot/Schwarz verfügbar</li>\n<li>Gesamtlänge bei Größe 128: ca. 97 cm</li>\n<li>Kleid in Größe 110 hat einen kleinen Nackenschlitz mit Knopf</li>\n</ul>\n",
  "short_description": "<p>Mittelalterliches Kinderkleid nIdeal für historische Darstellungen n100% Baumwolle, handwerklich gefertigt nMit goldener Bordüre und Schnürung nErhältlich in Blau/Blaugrau, Größen 110 bis 146</p>\n",
  "sku": "1280015150",
  "price": "39.99",
  "regular_price": "",
  "sale_price": "",
  "date_on_sale_from": null,
  "date_on_sale_from_gmt": null,
  "date_on_sale_to": null,
  "date_on_sale_to_gmt": null,
  "on_sale": false,
  "purchasable": true,
  "total_sales": 0,
  "virtual": false,
  "downloadable": false,
  "downloads": [],
  "download_limit": -1,
  "download_expiry": -1,
  "external_url": "",
  "button_text": "",
  "tax_status": "taxable",
  "tax_class": "",
  "manage_stock": true,
  "stock_quantity": 0,
  "backorders": "no",
  "backorders_allowed": false,
  "backordered": false,
  "low_stock_amount": null,
  "sold_individually": false,
  "weight": "0",
  "dimensions": {
    "length": "",
    "width": "",
    "height": ""
  },
  "shipping_required": true,
  "shipping_taxable": true,
  "shipping_class": "",
  "shipping_class_id": 0,
  "reviews_allowed": true,
  "average_rating": "0.00",
  "rating_count": 0,
  "upsell_ids": [],
  "cross_sell_ids": [],
  "parent_id": 0,
  "purchase_note": "",
  "categories": [
    {
      "id": 149,
      "name": "Kinderkleidung",
      "slug": "kinderkleidung"
    }
  ],
  "brands": [],
  "tags": [
    {
      "id": 160,
      "name": "Baumwolle",
      "slug": "baumwolle"
    },
    {
      "id": 200,
      "name": "Kinder",
      "slug": "kinder"
    },
    {
      "id": 206,
      "name": "Kinderkleider",
      "slug": "kinderkleider"
    },
    {
      "id": 189,
      "name": "Mittelalterkleid",
      "slug": "mittelalterkleid"
    }
  ],
  "images": [
    {
      "id": 6566,
      "date_created": "2025-10-10T19:10:07",
      "date_created_gmt": "2025-10-10T15:10:07",
      "date_modified": "2025-10-10T19:10:53",
      "date_modified_gmt": "2025-10-10T15:10:53",
      "src": "https://die-handelsgilde.de/wp-content/uploads/2025/10/1280015150c_kinderkleid_kleid_eleanor_mittelalterkleid_mittelalter_blau_langarm.webp",
      "name": "Kinder Mittelalterkleid Eleanor, langarm, blau",
      "alt": "Kinder Mittelalterkleid Eleanor, langarm, blau",
      "srcset": "https://die-handelsgilde.de/wp-content/uploads/2025/10/1280015150c_kinderkleid_kleid_eleanor_mittelalterkleid_mittelalter_blau_langarm.webp 1500w, https://die-handelsgilde.de/wp-content/uploads/2025/10/1280015150c_kinderkleid_kleid_eleanor_mittelalterkleid_mittelalter_blau_langarm-214x300.webp 214w, https://die-handelsgilde.de/wp-content/uploads/2025/10/1280015150c_kinderkleid_kleid_eleanor_mittelalterkleid_mittelalter_blau_langarm-731x1024.webp 731w, https://die-handelsgilde.de/wp-content/uploads/2025/10/1280015150c_kinderkleid_kleid_eleanor_mittelalterkleid_mittelalter_blau_langarm-768x1075.webp 768w, https://die-handelsgilde.de/wp-content/uploads/2025/10/1280015150c_kinderkleid_kleid_eleanor_mittelalterkleid_mittelalter_blau_langarm-1097x1536.webp 1097w, https://die-handelsgilde.de/wp-content/uploads/2025/10/1280015150c_kinderkleid_kleid_eleanor_mittelalterkleid_mittelalter_blau_langarm-1463x2048.webp 1463w, https://die-handelsgilde.de/wp-content/uploads/2025/10/1280015150c_kinderkleid_kleid_eleanor_mittelalterkleid_mittelalter_blau_langarm-1000x1400.webp 1000w",
      "sizes": "(max-width: 1500px) 100vw, 1500px",
      "thumbnail": "https://die-handelsgilde.de/wp-content/uploads/2025/10/1280015150c_kinderkleid_kleid_eleanor_mittelalterkleid_mittelalter_blau_langarm-500x600.webp"
    },
    {
      "id": 6567,
      "date_created": "2025-10-10T19:10:13",
      "date_created_gmt": "2025-10-10T15:10:13",
      "date_modified": "2025-10-10T19:10:53",
      "date_modified_gmt": "2025-10-10T15:10:53",
      "src": "https://die-handelsgilde.de/wp-content/uploads/2025/10/1280015150b_kinderkleid_kleid_eleanor_mittelalterkleid_mittelalter_blau_langarm.webp",
      "name": "Kinder Mittelalterkleid Eleanor, langarm, blau",
      "alt": "Kinder Mittelalterkleid Eleanor, langarm, blau",
      "srcset": "https://die-handelsgilde.de/wp-content/uploads/2025/10/1280015150b_kinderkleid_kleid_eleanor_mittelalterkleid_mittelalter_blau_langarm.webp 1500w, https://die-handelsgilde.de/wp-content/uploads/2025/10/1280015150b_kinderkleid_kleid_eleanor_mittelalterkleid_mittelalter_blau_langarm-214x300.webp 214w, https://die-handelsgilde.de/wp-content/uploads/2025/10/1280015150b_kinderkleid_kleid_eleanor_mittelalterkleid_mittelalter_blau_langarm-731x1024.webp 731w, https://die-handelsgilde.de/wp-content/uploads/2025/10/1280015150b_kinderkleid_kleid_eleanor_mittelalterkleid_mittelalter_blau_langarm-768x1075.webp 768w, https://die-handelsgilde.de/wp-content/uploads/2025/10/1280015150b_kinderkleid_kleid_eleanor_mittelalterkleid_mittelalter_blau_langarm-1097x1536.webp 1097w, https://die-handelsgilde.de/wp-content/uploads/2025/10/1280015150b_kinderkleid_kleid_eleanor_mittelalterkleid_mittelalter_blau_langarm-1463x2048.webp 1463w, https://die-handelsgilde.de/wp-content/uploads/2025/10/1280015150b_kinderkleid_kleid_eleanor_mittelalterkleid_mittelalter_blau_langarm-1000x1400.webp 1000w",
      "sizes": "(max-width: 1500px) 100vw, 1500px",
      "thumbnail": "https://die-handelsgilde.de/wp-content/uploads/2025/10/1280015150b_kinderkleid_kleid_eleanor_mittelalterkleid_mittelalter_blau_langarm-500x600.webp"
    },
    {
      "id": 6568,
      "date_created": "2025-10-10T19:10:20",
      "date_created_gmt": "2025-10-10T15:10:20",
      "date_modified": "2025-10-10T19:10:53",
      "date_modified_gmt": "2025-10-10T15:10:53",
      "src": "https://die-handelsgilde.de/wp-content/uploads/2025/10/1280015150f_kinderkleid_kleid_eleanor_mittelalterkleid_mittelalter_blau_langarm.webp",
      "name": "Kinder Mittelalterkleid Eleanor, langarm, blau",
      "alt": "Kinder Mittelalterkleid Eleanor, langarm, blau",
      "srcset": "https://die-handelsgilde.de/wp-content/uploads/2025/10/1280015150f_kinderkleid_kleid_eleanor_mittelalterkleid_mittelalter_blau_langarm.webp 1500w, https://die-handelsgilde.de/wp-content/uploads/2025/10/1280015150f_kinderkleid_kleid_eleanor_mittelalterkleid_mittelalter_blau_langarm-214x300.webp 214w, https://die-handelsgilde.de/wp-content/uploads/2025/10/1280015150f_kinderkleid_kleid_eleanor_mittelalterkleid_mittelalter_blau_langarm-731x1024.webp 731w, https://die-handelsgilde.de/wp-content/uploads/2025/10/1280015150f_kinderkleid_kleid_eleanor_mittelalterkleid_mittelalter_blau_langarm-768x1075.webp 768w, https://die-handelsgilde.de/wp-content/uploads/2025/10/1280015150f_kinderkleid_kleid_eleanor_mittelalterkleid_mittelalter_blau_langarm-1097x1536.webp 1097w, https://die-handelsgilde.de/wp-content/uploads/2025/10/1280015150f_kinderkleid_kleid_eleanor_mittelalterkleid_mittelalter_blau_langarm-1463x2048.webp 1463w, https://die-handelsgilde.de/wp-content/uploads/2025/10/1280015150f_kinderkleid_kleid_eleanor_mittelalterkleid_mittelalter_blau_langarm-1000x1400.webp 1000w",
      "sizes": "(max-width: 1500px) 100vw, 1500px",
      "thumbnail": "https://die-handelsgilde.de/wp-content/uploads/2025/10/1280015150f_kinderkleid_kleid_eleanor_mittelalterkleid_mittelalter_blau_langarm-500x600.webp"
    },
    {
      "id": 6569,
      "date_created": "2025-10-10T19:10:27",
      "date_created_gmt": "2025-10-10T15:10:27",
      "date_modified": "2025-10-10T19:10:53",
      "date_modified_gmt": "2025-10-10T15:10:53",
      "src": "https://die-handelsgilde.de/wp-content/uploads/2025/10/1280015150g_kinderkleid_kleid_eleanor_mittelalterkleid_mittelalter_blau_langarm.webp",
      "name": "Kinder Mittelalterkleid Eleanor, langarm, blau",
      "alt": "Kinder Mittelalterkleid Eleanor, langarm, blau",
      "srcset": "https://die-handelsgilde.de/wp-content/uploads/2025/10/1280015150g_kinderkleid_kleid_eleanor_mittelalterkleid_mittelalter_blau_langarm.webp 1500w, https://die-handelsgilde.de/wp-content/uploads/2025/10/1280015150g_kinderkleid_kleid_eleanor_mittelalterkleid_mittelalter_blau_langarm-214x300.webp 214w, https://die-handelsgilde.de/wp-content/uploads/2025/10/1280015150g_kinderkleid_kleid_eleanor_mittelalterkleid_mittelalter_blau_langarm-731x1024.webp 731w, https://die-handelsgilde.de/wp-content/uploads/2025/10/1280015150g_kinderkleid_kleid_eleanor_mittelalterkleid_mittelalter_blau_langarm-768x1075.webp 768w, https://die-handelsgilde.de/wp-content/uploads/2025/10/1280015150g_kinderkleid_kleid_eleanor_mittelalterkleid_mittelalter_blau_langarm-1097x1536.webp 1097w, https://die-handelsgilde.de/wp-content/uploads/2025/10/1280015150g_kinderkleid_kleid_eleanor_mittelalterkleid_mittelalter_blau_langarm-1463x2048.webp 1463w, https://die-handelsgilde.de/wp-content/uploads/2025/10/1280015150g_kinderkleid_kleid_eleanor_mittelalterkleid_mittelalter_blau_langarm-1000x1400.webp 1000w",
      "sizes": "(max-width: 1500px) 100vw, 1500px",
      "thumbnail": "https://die-handelsgilde.de/wp-content/uploads/2025/10/1280015150g_kinderkleid_kleid_eleanor_mittelalterkleid_mittelalter_blau_langarm-500x600.webp"
    },
    {
      "id": 6570,
      "date_created": "2025-10-10T19:10:33",
      "date_created_gmt": "2025-10-10T15:10:33",
      "date_modified": "2025-10-10T19:10:53",
      "date_modified_gmt": "2025-10-10T15:10:53",
      "src": "https://die-handelsgilde.de/wp-content/uploads/2025/10/1280015150h_kinderkleid_kleid_eleanor_mittelalterkleid_mittelalter_blau_langarm.webp",
      "name": "Kinder Mittelalterkleid Eleanor, langarm, blau",
      "alt": "Kinder Mittelalterkleid Eleanor, langarm, blau",
      "srcset": "https://die-handelsgilde.de/wp-content/uploads/2025/10/1280015150h_kinderkleid_kleid_eleanor_mittelalterkleid_mittelalter_blau_langarm.webp 1500w, https://die-handelsgilde.de/wp-content/uploads/2025/10/1280015150h_kinderkleid_kleid_eleanor_mittelalterkleid_mittelalter_blau_langarm-214x300.webp 214w, https://die-handelsgilde.de/wp-content/uploads/2025/10/1280015150h_kinderkleid_kleid_eleanor_mittelalterkleid_mittelalter_blau_langarm-731x1024.webp 731w, https://die-handelsgilde.de/wp-content/uploads/2025/10/1280015150h_kinderkleid_kleid_eleanor_mittelalterkleid_mittelalter_blau_langarm-768x1075.webp 768w, https://die-handelsgilde.de/wp-content/uploads/2025/10/1280015150h_kinderkleid_kleid_eleanor_mittelalterkleid_mittelalter_blau_langarm-1097x1536.webp 1097w, https://die-handelsgilde.de/wp-content/uploads/2025/10/1280015150h_kinderkleid_kleid_eleanor_mittelalterkleid_mittelalter_blau_langarm-1463x2048.webp 1463w, https://die-handelsgilde.de/wp-content/uploads/2025/10/1280015150h_kinderkleid_kleid_eleanor_mittelalterkleid_mittelalter_blau_langarm-1000x1400.webp 1000w",
      "sizes": "(max-width: 1500px) 100vw, 1500px",
      "thumbnail": "https://die-handelsgilde.de/wp-content/uploads/2025/10/1280015150h_kinderkleid_kleid_eleanor_mittelalterkleid_mittelalter_blau_langarm-500x600.webp"
    },
    {
      "id": 6571,
      "date_created": "2025-10-10T19:10:39",
      "date_created_gmt": "2025-10-10T15:10:39",
      "date_modified": "2025-10-10T19:10:53",
      "date_modified_gmt": "2025-10-10T15:10:53",
      "src": "https://die-handelsgilde.de/wp-content/uploads/2025/10/1280015150j_kinderkleid_kleid_eleanor_mittelalterkleid_mittelalter_blau_langarm.webp",
      "name": "Kinder Mittelalterkleid Eleanor, langarm, blau",
      "alt": "Kinder Mittelalterkleid Eleanor, langarm, blau",
      "srcset": "https://die-handelsgilde.de/wp-content/uploads/2025/10/1280015150j_kinderkleid_kleid_eleanor_mittelalterkleid_mittelalter_blau_langarm.webp 1500w, https://die-handelsgilde.de/wp-content/uploads/2025/10/1280015150j_kinderkleid_kleid_eleanor_mittelalterkleid_mittelalter_blau_langarm-214x300.webp 214w, https://die-handelsgilde.de/wp-content/uploads/2025/10/1280015150j_kinderkleid_kleid_eleanor_mittelalterkleid_mittelalter_blau_langarm-731x1024.webp 731w, https://die-handelsgilde.de/wp-content/uploads/2025/10/1280015150j_kinderkleid_kleid_eleanor_mittelalterkleid_mittelalter_blau_langarm-768x1075.webp 768w, https://die-handelsgilde.de/wp-content/uploads/2025/10/1280015150j_kinderkleid_kleid_eleanor_mittelalterkleid_mittelalter_blau_langarm-1097x1536.webp 1097w, https://die-handelsgilde.de/wp-content/uploads/2025/10/1280015150j_kinderkleid_kleid_eleanor_mittelalterkleid_mittelalter_blau_langarm-1463x2048.webp 1463w, https://die-handelsgilde.de/wp-content/uploads/2025/10/1280015150j_kinderkleid_kleid_eleanor_mittelalterkleid_mittelalter_blau_langarm-1000x1400.webp 1000w",
      "sizes": "(max-width: 1500px) 100vw, 1500px",
      "thumbnail": "https://die-handelsgilde.de/wp-content/uploads/2025/10/1280015150j_kinderkleid_kleid_eleanor_mittelalterkleid_mittelalter_blau_langarm-500x600.webp"
    }
  ],
  "attributes": [
    {
      "id": 1,
      "name": "Größe",
      "slug": "pa_groesse",
      "position": 0,
      "visible": true,
      "variation": true,
      "options": [
        "110",
        "128",
        "146"
      ]
    }
  ],
  "default_attributes": [],
  "variations": [],
  "grouped_products": [],
  "menu_order": 0,
  "price_html": "",
  "related_ids": [
    708,
    570,
    415,
    513,
    725
  ],
  "meta_data": [
    {
      "id": 125376,
      "key": "rank_math_internal_links_processed",
      "value": "1"
    },
    {
      "id": 125398,
      "key": "generator",
      "value": "importer-handelsgilde"
    },
    {
      "id": 125399,
      "key": "_unit",
      "value": ""
    },
    {
      "id": 125400,
      "key": "_unit_price_auto",
      "value": "no"
    },
    {
      "id": 125401,
      "key": "_sale_price_label",
      "value": ""
    },
    {
      "id": 125402,
      "key": "_sale_price_regular_label",
      "value": ""
    },
    {
      "id": 125403,
      "key": "_manufacturer_slug",
      "value": ""
    },
    {
      "id": 125404,
      "key": "_warranty_attachment_id",
      "value": ""
    },
    {
      "id": 125405,
      "key": "_safety_attachment_ids",
      "value": []
    },
    {
      "id": 125406,
      "key": "_min_age",
      "value": ""
    },
    {
      "id": 125407,
      "key": "_ts_gtin",
      "value": ""
    },
    {
      "id": 125408,
      "key": "_ts_mpn",
      "value": ""
    },
    {
      "id": 125409,
      "key": "_default_delivery_time",
      "value": ""
    },
    {
      "id": 125410,
      "key": "_delivery_time_countries",
      "value": []
    },
    {
      "id": 125411,
      "key": "_free_shipping",
      "value": "no"
    },
    {
      "id": 125412,
      "key": "_service",
      "value": "no"
    },
    {
      "id": 125413,
      "key": "_photovoltaic_system",
      "value": "no"
    },
    {
      "id": 125414,
      "key": "_used_good",
      "value": "no"
    },
    {
      "id": 125415,
      "key": "_defective_copy",
      "value": "no"
    },
    {
      "id": 125416,
      "key": "_wireless_electronic_device",
      "value": "no"
    },
    {
      "id": 125417,
      "key": "_device_contains_power_supply",
      "value": "no"
    },
    {
      "id": 125418,
      "key": "_device_charging_supports_usb_pd",
      "value": "no"
    },
    {
      "id": 125419,
      "key": "_is_food",
      "value": "no"
    },
    {
      "id": 125420,
      "key": "_differential_taxation",
      "value": "no"
    },
    {
      "id": 125421,
      "key": "_gzd_version",
      "value": "3.20.2"
    },
    {
      "id": 292327,
      "key": "_unit_price_regular",
      "value": ""
    },
    {
      "id": 292328,
      "key": "_unit_price_sale",
      "value": ""
    },
    {
      "id": 292329,
      "key": "_unit_price",
      "value": ""
    },
    {
      "id": 292330,
      "key": "_defect_description",
      "value": ""
    }
  ],
  "stock_status": "outofstock",
  "has_options": true,
  "post_password": "",
  "global_unique_id": "",
  "hs_code": "",
  "customs_description": "",
  "manufacture_country": "DE",
  "shipping_dimensions": {
    "length": "",
    "width": "",
    "height": ""
  },
  "unit": [],
  "unit_price": {
    "base": "",
    "product": "",
    "price_auto": false,
    "price": "",
    "price_regular": "",
    "price_sale": "",
    "price_html": ""
  },
  "mini_desc": "",
  "defect_description": "",
  "min_age": "",
  "gtin": "",
  "mpn": "",
  "sale_price_label": [],
  "sale_price_regular_label": [],
  "manufacturer": [],
  "safety_attachment_ids": [],
  "safety_instructions": "",
  "delivery_time": [],
  "country_specific_delivery_times": [],
  "free_shipping": false,
  "wireless_electronic_device": false,
  "device_contains_power_supply": false,
  "device_charging_supports_usb_pd": false,
  "device_charging_watt_min": "",
  "device_charging_watt_max": "",
  "service": false,
  "used_good": false,
  "defective_copy": false,
  "photovoltaic_system": false,
  "differential_taxation": false,
  "warranty_attachment_id": "",
  "is_food": false,
  "food": {
    "deposit_type": [],
    "deposit_quantity": 1,
    "deposit": 0,
    "ingredients": "",
    "nutrient_reference_value": "",
    "nutri_score": "",
    "alcohol_content": "",
    "allergen_ids": [],
    "nutrient_ids": [
      {
        "term": 0,
        "value": "",
        "ref_value": ""
      }
    ],
    "net_filling_quantity": "",
    "drained_weight": "",
    "description": "",
    "distributor": "",
    "place_of_origin": ""
  },
  "_links": {
    "self": [
      {
        "href": "https://die-handelsgilde.de/wp-json/wc/v3/products/6572",
        "targetHints": {
          "allow": [
            "GET",
            "POST",
            "PUT",
            "PATCH",
            "DELETE"
          ]
        }
      }
    ],
    "collection": [
      {
        "href": "https://die-handelsgilde.de/wp-json/wc/v3/products"
      }
    ]
  }
}